Metadata-Version: 2.4
Name: star_shine
Version: 0.3.6
Summary: Satellite Time-series Analysis Routine using Sinusoids and Harmonics through Iterative Non-linear Extraction
Author: Luc IJspeert
License: GPL-3.0-only
Project-URL: repository, https://github.com/LucIJspeert/star_shine
Classifier: Development Status :: 4 - Beta
Classifier: Intended Audience :: Science/Research
Classifier: Topic :: Scientific/Engineering :: Astronomy
Classifier: License :: OSI Approved :: GNU General Public License v3 (GPLv3)
Classifier: Programming Language :: Python :: 3
Requires-Python: <3.13,>=3.11
License-File: LICENCE.md
Requires-Dist: numpy<3.0.0,>=1.20.3
Requires-Dist: scipy<2.0.0,>=1.7.3
Requires-Dist: numba<1.0.0,>=0.55.1
Requires-Dist: h5py<4.0.0,>=3.7.0
Requires-Dist: astropy<8.0.0,>=4.3.1
Requires-Dist: pandas<3.0.0,>=1.2.3
Requires-Dist: matplotlib<4.0.0,>=3.5.3
Requires-Dist: pyyaml<7.0.0,>=6.0.2
Provides-Extra: mcmc
Requires-Dist: pymc<6.0.0,>=5.0.0; extra == "mcmc"
Requires-Dist: arviz<1.0.0,>=0.11.4; extra == "mcmc"
Requires-Dist: fastprogress<2.0.0,>=1.0.0; extra == "mcmc"
Provides-Extra: gui
Requires-Dist: pyside6<7.0.0,>=6.6.0; extra == "gui"
Dynamic: license-file
